dicelib/connectivity.cpython-310-x86_64-linux-gnu.so
dicelib/image.cpython-310-x86_64-linux-gnu.so
dicelib/streamline.cpython-310-x86_64-linux-gnu.so
dicelib/ui.py
dicelib/__init__.py
dicelib/tsf.cpython-310-x86_64-linux-gnu.so
dicelib/tractogram.cpython-310-x86_64-linux-gnu.so
dicelib/utils.py
dicelib/clustering.cpython-310-x86_64-linux-gnu.so
dicelib/scripts/dice_image.py
dicelib/scripts/dice_connectome.py
dicelib/scripts/dice_tractogram.py
dmri_dicelib-1.2.0.dist-info/METADATA
dmri_dicelib-1.2.0.dist-info/RECORD
dmri_dicelib-1.2.0.dist-info/top_level.txt
dmri_dicelib-1.2.0.dist-info/WHEEL
dmri_dicelib-1.2.0.dist-info/LICENSE
dmri_dicelib-1.2.0.dist-info/entry_points.txt
