Metadata-Version: 2.2
Name: dmri-dicelib
Version: 1.2.0
Summary: Software library of the DICE Lab (Diffusion Imaging and Connectivity Estimation Laboratory)
Author-email: DICE Lab <DICE_lab@strutture.univr.it>
Maintainer-email: DICE Lab <DICE_lab@strutture.univr.it>
License: ################################################################################
Project-URL: Homepage, https://github.com/dice-lab-vr/dicelib.git
Project-URL: Documentation, https://github.com/dice-lab-vr/dicelib/blob/master/README.md
Project-URL: Repository, https://github.com/dice-lab-vr/dicelib.git
Project-URL: Issues, https://github.com/dice-lab-vr/dicelib/issues
Project-URL: Changelog, https://github.com/dice-lab-vr/dicelib/blob/master/CHANGELOG.md
Keywords: Neuroimaging
Classifier: Intended Audience :: Science/Research
Classifier: Topic :: Scientific/Engineering :: Image Processing
Classifier: License :: Other/Proprietary License
Classifier: Programming Language :: C++
Classifier: Programming Language :: Cython
Classifier: Programming Language :: Python :: 3
Classifier: Programming Language :: Python :: 3 :: Only
Classifier: Programming Language :: Python :: 3.8
Classifier: Programming Language :: Python :: 3.9
Classifier: Programming Language :: Python :: 3.10
Classifier: Programming Language :: Python :: 3.11
Classifier: Programming Language :: Python :: 3.12
Requires-Python: >=3.8
License-File: LICENSE
Requires-Dist: cython>=3.0.10
Requires-Dist: nibabel>=5.2.1
Requires-Dist: numpy>=1.24.4
Requires-Dist: psutil>=5.9.8
Requires-Dist: pywin32>=306; sys_platform == "win32"
Requires-Dist: scipy>=1.10.1
